block3.cpython-38-x86_64-linux-gnu.so
pyblock3/hamiltonian.py
pyblock3/__init__.py
pyblock3/fcidump.py
pyblock3/symbolic/__init__.py
pyblock3/symbolic/expr.py
pyblock3/symbolic/symbolic.py
pyblock3/symbolic/symbolic_mpo.py
pyblock3/algebra/__init__.py
pyblock3/algebra/fermion_symmetry.py
pyblock3/algebra/symmetry.py
pyblock3/algebra/core.py
pyblock3/algebra/integrate.py
pyblock3/algebra/funcs.py
pyblock3/algebra/fermion.py
pyblock3/algebra/mps.py
pyblock3/algebra/flat_functor.py
pyblock3/algebra/flat.py
pyblock3/algebra/fermion_ops.py
pyblock3/algebra/linalg.py
pyblock3/algebra/fermion_setting.py
pyblock3/algebra/mpe.py
pyblock3/algebra/fermion_encoding.py
pyblock3/algebra/impl/__init__.py
pyblock3/algebra/impl/flat.py
pyblock3/algorithms/__init__.py
pyblock3/algorithms/core.py
pyblock3/algorithms/dmrg.py
pyblock3/algorithms/green.py
pyblock3/algorithms/linear.py
pyblock3/algorithms/tddmrg.py
pyblock3/block2/io.py
pyblock3/block2/__init__.py
pyblock3/block2/hamil.py
pyblock3_general.libs/libmkl_intel_lp64-7fce225f.so
pyblock3_general.libs/libgomp-f7e03b3e.so.1.0.0
pyblock3_general.libs/libmkl_avx2.so
pyblock3_general.libs/libmkl_gnu_thread-22473446.so
pyblock3_general.libs/libmkl_avx512.so
pyblock3_general.libs/libmkl_core-fbf20eba.so
pyblock3_general-0.2.1.dist-info/LICENSE
pyblock3_general-0.2.1.dist-info/top_level.txt
pyblock3_general-0.2.1.dist-info/RECORD
pyblock3_general-0.2.1.dist-info/WHEEL
pyblock3_general-0.2.1.dist-info/METADATA
