Metadata-Version: 2.1
Name: pyblock3-general
Version: 0.2.1
Summary: An efficient python block-sparse tensor and MPS/DMRG library.
Home-page: https://github.com/block-hczhai/pyblock3-preview
Author: Huanchen Zhai, Yang Gao, and Garnet K.-L. Chan
Author-email: hczhai@ucla.edu
License: LICENSE
Platform: UNKNOWN
License-File: LICENSE
Requires-Dist: mkl (==2019)
Requires-Dist: mkl-include
Requires-Dist: numpy
Requires-Dist: psutil
Requires-Dist: pybind11
Requires-Dist: intel-openmp
Requires-Dist: cmake (==3.17)
